CHANGES.rst
CONTRIBUTORS.rst
DEVELOP.rst
LICENSE.GPL
LICENSE.rst
MANIFEST.in
Makefile
README.rst
requirements.txt
setup.cfg
setup.py
docs/conf.py
docs/index.rst
src/imio/__init__.py
src/imio.prometheus.egg-info/PKG-INFO
src/imio.prometheus.egg-info/SOURCES.txt
src/imio.prometheus.egg-info/dependency_links.txt
src/imio.prometheus.egg-info/entry_points.txt
src/imio.prometheus.egg-info/namespace_packages.txt
src/imio.prometheus.egg-info/not-zip-safe
src/imio.prometheus.egg-info/requires.txt
src/imio.prometheus.egg-info/top_level.txt
src/imio/prometheus/__init__.py
src/imio/prometheus/browser.py
src/imio/prometheus/configure.zcml
src/imio/prometheus/setuphandlers.py
src/imio/prometheus/testing.py
src/imio/prometheus/locales/README.rst
src/imio/prometheus/locales/__init__.py
src/imio/prometheus/locales/imio.prometheus.pot
src/imio/prometheus/locales/update.py
src/imio/prometheus/locales/update.sh
src/imio/prometheus/locales/en/LC_MESSAGES/imio.prometheus.po
src/imio/prometheus/profiles/default/metadata.xml
src/imio/prometheus/tests/__init__.py
src/imio/prometheus/tests/test_view.py