Metadata-Version: 2.1
Name: imio.prometheus
Version: 1.0.1
Summary: Add some iMio informations on prometheus metrics view
Home-page: https://github.com/IMIO/imio.prometheus
Author: Benoît Suttor
Author-email: benoit.suttor@imio.be
License: GPL version 2
Project-URL: PyPI, https://pypi.python.org/pypi/imio.prometheus
Project-URL: Source, https://github.com/IMIO/imio.prometheus
Project-URL: Tracker, https://github.com/IMIO/imio.prometheus/issues
Keywords: Python Plone
Platform: UNKNOWN
Classifier: Environment :: Web Environment
Classifier: Framework :: Plone
Classifier: Framework :: Plone :: Addon
Classifier: Framework :: Plone :: 4.3
Classifier: Framework :: Plone :: 5.2
Classifier: Framework :: Plone :: 6.0
Classifier: Programming Language :: Python
Classifier: Programming Language :: Python :: 2.7
Classifier: Programming Language :: Python :: 3.6
Classifier: Programming Language :: Python :: 3.7
Classifier: Programming Language :: Python :: 3.8
Classifier: Operating System :: OS Independent
Classifier: License :: OSI Approved :: GNU General Public License v2 (GPLv2)
Provides-Extra: test
